{
  "__data_type": "UTI ",
  "AddCost": {
    "type": "dword",
    "value": 0
  },
  "BaseItem": {
    "type": "int",
    "value": 0
  },
  "Charges": {
    "type": "byte",
    "value": 0
  },
  "Comment": {
    "type": "cexostring",
    "value": ""
  },
  "Cost": {
    "type": "dword",
    "value": 33640
  },
  "Cursed": {
    "type": "byte",
    "value": 0
  },
  "DescIdentified": {
    "type": "cexolocstring",
    "value": {
      "0": "This short sword was crafted by highly skilled halfling weapon smiths in conjunction with three priests of Urogalan, the Black Hound. The priests of the god of the dead commissioned and enchanted the sword for a famous halfling adventurer named Eriadon Oakhollow. Eriadon was well known for his fight against those who would defile the tombs of his people. The sword has a dull, even blade with deep engraving on one side. The engraving is in Thorass and lists, in various tables, all of the days of a tenday, months of the year, cycles of the moon, major halfling festivals and observances, and the years of Eriadon's life. The other side of the blade simply features the maker's mark, a black hound's head, and the words \"THE SWORD OF DAYS.\" Tarnished silver in the engraving lines keeps the words and images dark. Upon Eriadon's death, the sword was passed on to a traveling priest of Arvoreen the Defender who is believed to have died fighting goblins in the High Moor."
    }
  },
  "Description": {
    "type": "cexolocstring",
    "value": {
      "0": ""
    }
  },
  "Identified": {
    "type": "byte",
    "value": 0
  },
  "LocalizedName": {
    "type": "cexolocstring",
    "value": {
      "0": "The Sword of Days"
    }
  },
  "ModelPart1": {
    "type": "byte",
    "value": 252
  },
  "ModelPart2": {
    "type": "byte",
    "value": 191
  },
  "ModelPart3": {
    "type": "byte",
    "value": 121
  },
  "PaletteID": {
    "type": "byte",
    "value": 38
  },
  "Plot": {
    "type": "byte",
    "value": 0
  },
  "PropertiesList": {
    "type": "list",
    "value": [
      {
        "__struct_id": 0,
        "ChanceAppear": {
          "type": "byte",
          "value": 100
        },
        "CostTable": {
          "type": "byte",
          "value": 2
        },
        "CostValue": {
          "type": "word",
          "value": 3
        },
        "Param1": {
          "type": "byte",
          "value": 255
        },
        "Param1Value": {
          "type": "byte",
          "value": 0
        },
        "PropertyName": {
          "type": "word",
          "value": 6
        },
        "Subtype": {
          "type": "word",
          "value": 0
        }
      },
      {
        "__struct_id": 0,
        "ChanceAppear": {
          "type": "byte",
          "value": 100
        },
        "CostTable": {
          "type": "byte",
          "value": 16
        },
        "CostValue": {
          "type": "word",
          "value": 153
        },
        "Param1": {
          "type": "byte",
          "value": 255
        },
        "Param1Value": {
          "type": "byte",
          "value": 0
        },
        "PropertyName": {
          "type": "word",
          "value": 53
        },
        "Subtype": {
          "type": "word",
          "value": 0
        }
      }
    ]
  },
  "StackSize": {
    "type": "word",
    "value": 1
  },
  "Stolen": {
    "type": "byte",
    "value": 0
  },
  "Tag": {
    "type": "cexostring",
    "value": "TheSwordofDays"
  },
  "TemplateResRef": {
    "type": "resref",
    "value": "ss_swordofdays"
  }
}
